<?xml version="1.0" encoding="UTF-8"?><record_update table="sys_alias"><sys_alias action="DELETE"><configuration_template/><connection_type>sys_connection</connection_type><id>x_snc_fadv.testtt</id><multiple_connections>false</multiple_connections><name>testtt</name><retry_policy display_value="Default HTTP Retry Policy">ef751ff07301330025d71afe2ff6a7f9</retry_policy><sys_class_name>sys_alias</sys_class_name><sys_created_by>sheetals</sys_created_by><sys_created_on>2019-11-27 11:05:39</sys_created_on><sys_id>f76a2dfedb59c0143e146583ca96198f</sys_id><sys_mod_count>0</sys_mod_count><sys_name>x_snc_fadv.testtt</sys_name><sys_package display_value="First Advantage Spoke" source="x_snc_fadv">56e01698dbb333403e146583ca96192d</sys_package><sys_policy/><sys_scope display_value="First Advantage Spoke">56e01698dbb333403e146583ca96192d</sys_scope><sys_update_name>sys_alias_f76a2dfedb59c0143e146583ca96198f</sys_update_name><sys_updated_by>sheetals</sys_updated_by><sys_updated_on>2019-11-27 11:05:39</sys_updated_on><type>connection</type></sys_alias></record_update>